wyn_transformers/__init__.py
wyn_transformers/inference.py
wyn_transformers/push_to_hub.py
wyn_transformers/transformers.py
wyn_transformers-0.1.8.dist-info/METADATA
wyn_transformers-0.1.8.dist-info/WHEEL
wyn_transformers-0.1.8.dist-info/RECORD
