Metadata-Version: 2.1
Name: wyn-transformers
Version: 0.1.8
Summary: The official package to train a transformer from scratch.
Author: Yiqiao Yin
Author-email: eagle0504@gmail.com
Requires-Python: >=3.10,<4.0
Classifier: Programming Language :: Python :: 3
Classifier: Programming Language :: Python :: 3.10
Classifier: Programming Language :: Python :: 3.11
Classifier: Programming Language :: Python :: 3.12
Requires-Dist: huggingface-hub (==0.23.5)
Requires-Dist: matplotlib (==3.7.1)
Requires-Dist: numpy (==1.26.4)
Requires-Dist: tensorflow (==2.17.0)
Requires-Dist: tensorflow-datasets (==4.9.6)
